[
  {
    "id": 16246571,
    "slug": "qoaly0",
    "title": "test1",
    "book_id": 2031735,
    "book": {
      "id": 2031735,
      "type": "Book",
      "slug": "blog",
      "name": "blog",
      "user_id": 527662,
      "description": "",
      "creator_id": 527662,
      "public": 0,
      "items_count": 1,
      "likes_count": 0,
      "watches_count": 1,
      "content_updated_at": "2020-11-19T21:36:56.450Z",
      "updated_at": "2020-11-19T21:37:36.000Z",
      "created_at": "2020-11-19T13:59:05.000Z",
      "namespace": "jlovec/blog",
      "user": {
        "id": 527662,
        "type": "User",
        "login": "jlovec",
        "name": "JloveC",
        "description": null,
        "avatar_url": "https://cdn.nlark.com/yuque/0/2019/jpeg/anonymous/1570782746224-c1f159c7-2818-436b-bfbb-82fbffe4723f.jpeg",
        "books_count": 10,
        "public_books_count": 1,
        "followers_count": 0,
        "following_count": 0,
        "created_at": "2019-10-11T08:32:53.000Z",
        "updated_at": "2020-11-19T13:59:05.000Z",
        "_serializer": "v2.user"
      },
      "_serializer": "v2.book"
    },
    "user_id": 527662,
    "creator": {
      "id": 527662,
      "type": "User",
      "login": "jlovec",
      "name": "JloveC",
      "description": null,
      "avatar_url": "https://cdn.nlark.com/yuque/0/2019/jpeg/anonymous/1570782746224-c1f159c7-2818-436b-bfbb-82fbffe4723f.jpeg",
      "books_count": 10,
      "public_books_count": 1,
      "followers_count": 0,
      "following_count": 0,
      "created_at": "2019-10-11T08:32:53.000Z",
      "updated_at": "2020-11-19T13:59:05.000Z",
      "_serializer": "v2.user"
    },
    "format": "lake",
    "body": "heelo<br />\n<br />\n<br />123\n",
    "body_draft": "heelo<br />\n<br />\n<br />123\n",
    "body_html": "<!doctype html><div class=\"lake-content-editor-core lake-engine lake-typography-classic\" data-lake-element=\"root\" data-selection-undefined=\"%7B%22path%22%3A%5B%5B3%2C0%2C3%5D%2C%5B3%2C0%2C3%5D%5D%2C%22active%22%3Atrue%7D\"><p data-lake-id=\"a20d224c568e48b9d67847a2c66a8c01_p_0\" style=\"font-size: 14px; color: rgb(38, 38, 38); line-height: 1.74; letter-spacing: 0.05em; outline-style: none; overflow-wrap: break-word; margin: 0px;\">heelo</p><p data-lake-id=\"f9be41fd92ee05bf0dc738d8994c7318\" style=\"font-size: 14px; color: rgb(38, 38, 38); line-height: 1.74; letter-spacing: 0.05em; outline-style: none; overflow-wrap: break-word; margin: 0px;\"><br></p><p data-lake-id=\"4dd1cc6f144fd0720caea11db09cc20e\" style=\"font-size: 14px; color: rgb(38, 38, 38); line-height: 1.74; letter-spacing: 0.05em; outline-style: none; overflow-wrap: break-word; margin: 0px;\"><br></p><p data-lake-id=\"541efbf556c58a4914e2256eb9f052be\" style=\"font-size: 14px; color: rgb(38, 38, 38); line-height: 1.74; letter-spacing: 0.05em; outline-style: none; overflow-wrap: break-word; margin: 0px;\">123</p></div>",
    "body_lake": "<!doctype lake><meta name=\"doc-version\" content=\"1\" /><meta name=\"viewport\" content=\"fixed\" /><meta name=\"typography\" content=\"classic\" /><p data-lake-id=\"a20d224c568e48b9d67847a2c66a8c01_p_0\">heelo</p><p data-lake-id=\"f9be41fd92ee05bf0dc738d8994c7318\"><br /></p><p data-lake-id=\"4dd1cc6f144fd0720caea11db09cc20e\"><br /></p><p data-lake-id=\"541efbf556c58a4914e2256eb9f052be\">123</p>",
    "body_draft_lake": "<!doctype lake><meta name=\"doc-version\" content=\"1\" /><meta name=\"viewport\" content=\"fixed\" /><meta name=\"typography\" content=\"classic\" /><p data-lake-id=\"a20d224c568e48b9d67847a2c66a8c01_p_0\">heelo</p><p data-lake-id=\"f9be41fd92ee05bf0dc738d8994c7318\"><br /></p><p data-lake-id=\"4dd1cc6f144fd0720caea11db09cc20e\"><br /></p><p data-lake-id=\"541efbf556c58a4914e2256eb9f052be\">123</p>",
    "public": 1,
    "status": 1,
    "view_status": 0,
    "read_status": 1,
    "likes_count": 0,
    "comments_count": 0,
    "content_updated_at": "2020-11-19T21:31:16.000Z",
    "deleted_at": null,
    "created_at": "2020-11-19T21:26:24.000Z",
    "updated_at": "2020-11-19T21:31:16.000Z",
    "published_at": "2020-11-19T21:31:16.000Z",
    "first_published_at": "2020-11-19T21:26:33.000Z",
    "word_count": 2,
    "cover": null,
    "description": "heelo123",
    "custom_description": null,
    "hits": 0,
    "_serializer": "v2.doc_detail"
  }
]